<Properties StartupConfiguration="{74077BC4-2025-ACD0-AEB0-331C8A57EA3D}|">
  <MonoDevelop.Ide.Workbench ActiveDocument="Assets/Scripts/Torch.cs">
    <Files>
      <File FileName="Assets/Scripts/PlayerController.cs" Line="57" Column="31" />
      <File FileName="Assets/Scripts/FireController.cs" Line="33" Column="13" />
      <File FileName="Assets/Scripts/Torch.cs" Line="13" Column="1" />
      <File FileName="Assets/Scripts/Stick.cs" Line="26" Column="10" />
      <File FileName="Assets/Scripts/AIController.cs" Line="78" Column="50" />
    </Files>
  </MonoDevelop.Ide.Workbench>
  <MonoDevelop.Ide.ItemProperties.Game__Jam__1 PreferredExecutionTarget="Unity.Editor" />
  <MonoDevelop.Ide.DebuggingService.PinnedWatches />
  <MonoDevelop.Ide.Workspace ActiveConfiguration="Debug" />
  <MonoDevelop.Ide.ItemProperties.Assembly-CSharp PreferredExecutionTarget="Unity.Editor" />
  <MonoDevelop.Ide.DebuggingService.Breakpoints>
    <BreakpointStore />
  </MonoDevelop.Ide.DebuggingService.Breakpoints>
  <MultiItemStartupConfigurations />
</Properties>